BraineryWiz/FEMWiz.cp310-win_amd64.pyd
BraineryWiz/FEMWiz.cp311-win_amd64.pyd
BraineryWiz/FEMWiz.cp312-win_amd64.pyd
BraineryWiz/FEMWiz.pyd
BraineryWiz/PlotAnimation.cp310-win_amd64.pyd
BraineryWiz/PlotAnimation.cp311-win_amd64.pyd
BraineryWiz/PlotAnimation.cp312-win_amd64.pyd
BraineryWiz/PlotAnimation.pyd
BraineryWiz/PlotDefo.cp310-win_amd64.pyd
BraineryWiz/PlotDefo.cp311-win_amd64.pyd
BraineryWiz/PlotDefo.cp312-win_amd64.pyd
BraineryWiz/PlotDefo.pyd
BraineryWiz/PlotModeShape.cp310-win_amd64.pyd
BraineryWiz/PlotModeShape.cp311-win_amd64.pyd
BraineryWiz/PlotModeShape.cp312-win_amd64.pyd
BraineryWiz/PlotModeShape.pyd
BraineryWiz/PlotModel.cp310-win_amd64.pyd
BraineryWiz/PlotModel.cp311-win_amd64.pyd
BraineryWiz/PlotModel.cp312-win_amd64.pyd
BraineryWiz/PlotModel.pyd
BraineryWiz/RealTime.cp310-win_amd64.pyd
BraineryWiz/RealTime.cp311-win_amd64.pyd
BraineryWiz/RealTime.cp312-win_amd64.pyd
BraineryWiz/RealTime.pyd
BraineryWiz/_DFunctions.cp310-win_amd64.pyd
BraineryWiz/_DFunctions.cp311-win_amd64.pyd
BraineryWiz/_DFunctions.cp312-win_amd64.pyd
BraineryWiz/_DFunctions.pyd
BraineryWiz/_PlotData.cp310-win_amd64.pyd
BraineryWiz/_PlotData.cp311-win_amd64.pyd
BraineryWiz/_PlotData.cp312-win_amd64.pyd
BraineryWiz/_PlotData.pyd
BraineryWiz/__init__.py
BraineryWiz/version.py
BraineryWiz-0.96.1.dist-info/METADATA
BraineryWiz-0.96.1.dist-info/WHEEL
BraineryWiz-0.96.1.dist-info/top_level.txt
BraineryWiz-0.96.1.dist-info/RECORD
