Metadata-Version: 2.1
Name: BraineryWiz
Version: 0.96.1
Summary: OpenSees Plotting Package
Home-page: https://github.com/bijanseif/BraineryWiz
Author: Bijan Sayyafzadeh
Author-email: <BraineryWiz@Gmail.com>
Keywords: python,opensees,Modeling,Dynamic
Classifier: Programming Language :: Python :: 3.11
Classifier: Topic :: Software Development :: Libraries :: Python Modules
Classifier: Operating System :: Microsoft :: Windows
Requires-Dist: openseespy
Requires-Dist: numpy
Requires-Dist: plotly
Requires-Dist: scipy
Requires-Dist: pillow
Requires-Dist: kaleido
Requires-Dist: tqdm
Requires-Dist: ipywidgets
